LICENCE
input4mips_validation-0.20.1.dist-info/METADATA
input4mips_validation-0.20.1.dist-info/WHEEL
input4mips_validation-0.20.1.dist-info/entry_points.txt
input4mips_validation-0.20.1.dist-info/licenses/LICENCE
input4mips_validation/__init__.py
input4mips_validation/attrs_helpers.py
input4mips_validation/cli/__init__.py
input4mips_validation/cli/common_arguments_and_options.py
input4mips_validation/cli/db.py
input4mips_validation/cvs/__init__.py
input4mips_validation/cvs/activity_id.py
input4mips_validation/cvs/author.py
input4mips_validation/cvs/cvs.py
input4mips_validation/cvs/drs.py
input4mips_validation/cvs/exceptions.py
input4mips_validation/cvs/institution_id.py
input4mips_validation/cvs/license.py
input4mips_validation/cvs/loading.py
input4mips_validation/cvs/loading_raw.py
input4mips_validation/cvs/source_id/__init__.py
input4mips_validation/cvs/source_id/values.py
input4mips_validation/database/__init__.py
input4mips_validation/database/creation.py
input4mips_validation/database/database.py
input4mips_validation/database/raw.py
input4mips_validation/dataset/__init__.py
input4mips_validation/dataset/dataset.py
input4mips_validation/dataset/metadata.py
input4mips_validation/dataset/metadata_data_producer_minimum.py
input4mips_validation/dataset/metadata_data_producer_multiple_variable_minimum.py
input4mips_validation/deprecation.py
input4mips_validation/exceptions.py
input4mips_validation/hashing.py
input4mips_validation/inference/__init__.py
input4mips_validation/inference/from_data.py
input4mips_validation/io.py
input4mips_validation/logging.py
input4mips_validation/logging_config.py
input4mips_validation/parallelisation.py
input4mips_validation/py.typed
input4mips_validation/serialisation.py
input4mips_validation/testing.py
input4mips_validation/upload_ftp.py
input4mips_validation/validation/Conventions.py
input4mips_validation/validation/__init__.py
input4mips_validation/validation/allowed_characters.py
input4mips_validation/validation/cf_checker.py
input4mips_validation/validation/comment.py
input4mips_validation/validation/creation_date.py
input4mips_validation/validation/database.py
input4mips_validation/validation/datasets_to_write_to_disk.py
input4mips_validation-0.20.1.dist-info/RECORD
